bulk_checksum/compare.py
bulk_checksum/generate.py
bulk_checksum-0.0.1.dist-info/METADATA
bulk_checksum-0.0.1.dist-info/WHEEL
bulk_checksum-0.0.1.dist-info/entry_points.txt
bulk_checksum-0.0.1.dist-info/top_level.txt
bulk_checksum-0.0.1.dist-info/RECORD
