Metadata-Version: 2.1
Name: bulk_checksum
Version: 0.0.1
Summary: CLI utility for verifiying bulk file copying
Requires-Python: >=3.9
Requires-Dist: click ~=8.1.7
